swuploader
