Metadata-Version: 1.0
Name: swuploader
Version: 0.1.4
Summary: Easy to use bulk model uploader for Shapeways.com API
Home-page: http://github.com/brettlangdon/swuploader
Author: Brett Langdon
Author-email: brett@blangdon.com
License: UNKNOWN
Platform: UNKNOWN
